{
    "hex-row-one":{
        "row-one-hex-one": {
            "income": ".50",
            "terrain": "sea",
            "army": {
                "isArmy": false,
                "currentArmy": []
            },
            "position": "0:0",
            "avaiableMoveLocation": ["0:1", "1:0"]

        },
        "row-one-hex-two": {
            "income": ".50",
            "terrain": "sea",
            "army": {
                "isArmy": false,
                "currentArmy": []
            },
            "position": "0:1",
            "avaiableMoveLocation": ["0:1", "1:0"]

        },
        "row-one-hex-three": {
            "income": ".50",
            "terrain": "sea",
            "army": {
                "isArmy": false,
                "currentArmy": []
            },
            "position": "0:2",
            "avaiableMoveLocation": ["0:1", "1:0"]

        },
        "row-one-hex-four": {
            "income": ".50",
            "terrain": "sea",
            "army": {
                "isArmy": false,
                "currentArmy": []
            },
            "position": "0:3",
            "avaiableMoveLocation": ["0:1", "1:0"]

        },
        "row-one-hex-five": {
            "income": ".50",
            "terrain": "sea",
            "army": {
                "isArmy": false,
                "currentArmy": []
            },
            "position": "0:4",
            "avaiableMoveLocation": ["0:1", "1:0"]

        },
        "row-one-hex-six": {
            "income": ".50",
            "terrain": "sea",
            "army": {
                "isArmy": false,
                "currentArmy": []
            },
            "position": "0:5",
            "avaiableMoveLocation": ["0:1", "1:0"]

        },
        "row-one-hex-seven": {
            "income": ".50",
            "terrain": "sea",
            "army": {
                "isArmy": false,
                "currentArmy": []
            },
            "position": "0:6",
            "avaiableMoveLocation": ["0:1", "1:0"]

        },
        "row-one-hex-eight": {
            "income": ".50",
            "terrain": "sea",
            "army": {
                "isArmy": false,
                "currentArmy": []
            },
            "position": "0:7",
            "avaiableMoveLocation": ["0:1", "1:0"]

        },
        "row-one-hex-nine": {
            "income": ".50",
            "terrain": "sea",
            "army": {
                "isArmy": false,
                "currentArmy": []
            },
            "position": "0:8",
            "avaiableMoveLocation": ["0:1", "1:0"]

        },
        "row-one-hex-ten": {
            "income": ".50",
            "terrain": "sea",
            "army": {
                "isArmy": false,
                "currentArmy": []
            },
            "position": "0:9",
            "avaiableMoveLocation": ["0:1", "1:0"]

        },
        "row-one-hex-eleven": {
            "income": ".50",
            "terrain": "sea",
            "army": {
                "isArmy": false,
                "currentArmy": []
            },
            "position": "0:10",
            "avaiableMoveLocation": ["0:1", "1:0"]

        },
        "row-one-hex-twelve": {
            "income": ".50",
            "terrain": "sea",
            "army": {
                "isArmy": false,
                "currentArmy": []
            },
            "position": "0:11",
            "avaiableMoveLocation": ["0:1", "1:0"]

        },
        "row-one-hex-thirteen": {
            "income": ".50",
            "terrain": "sea",
            "army": {
                "isArmy": false,
                "currentArmy": []
            },
            "position": "0:12",
            "avaiableMoveLocation": ["0:1", "1:0"]

        },
        "row-one-hex-fourteen": {
            "income": ".50",
            "terrain": "sea",
            "army": {
                "isArmy": false,
                "currentArmy": []
            },
            "position": "0:13",
            "avaiableMoveLocation": ["0:1", "1:0"]

        },
        "row-one-hex-fifteen": {
            "income": ".50",
            "terrain": "sea",
            "army": {
                "isArmy": false,
                "currentArmy": []
            },
            "position": "0:14",
            "avaiableMoveLocation": ["0:1", "1:0"]

        },
        "row-one-hex-sixteen": {
            "income": ".50",
            "terrain": "sea",
            "army": {
                "isArmy": false,
                "currentArmy": []
            },
            "position": "0:15",
            "avaiableMoveLocation": ["0:1", "1:0"]

        },
        "row-one-hex-seventeen": {
            "income": ".50",
            "terrain": "sea",
            "army": {
                "isArmy": false,
                "currentArmy": []
            },
            "position": "0:16",
            "avaiableMoveLocation": ["0:1", "1:0"]

        }
    },
    "hex-row-two":{
        "row-two-hex-one": {
            "income": ".50",
            "terrain": "sea",
            "army": {
                "isArmy": false,
                "currentArmy": []
            },
            "position": "1:0",
            "avaiableMoveLocation": ["0:1", "1:0"]
        },
        "row-two-hex-two": {
            "income": ".50",
            "terrain": "sea",
            "army": {
                "isArmy": false,
                "currentArmy": []
            },
            "position": "1:1",
            "avaiableMoveLocation": ["0:1", "1:0"]

        },
        "row-two-hex-three": {
            "income": ".50",
            "terrain": "sea",
            "army": {
                "isArmy": false,
                "currentArmy": []
            },
            "position": "1:2",
            "avaiableMoveLocation": ["0:1", "1:0"]

        },
        "row-two-hex-four": {
            "income": ".50",
            "terrain": "sea",
            "army": {
                "isArmy": false,
                "currentArmy": []
            },
            "position": "1:3",
            "avaiableMoveLocation": ["0:1", "1:0"]

        },
        "row-two-hex-five": {
            "income": ".50",
            "terrain": "sea",
            "army": {
                "isArmy": false,
                "currentArmy": []
            },
            "position": "1:4",
            "avaiableMoveLocation": ["0:1", "1:0"]

        },
        "row-two-hex-six": {
            "income": ".50",
            "terrain": "sea",
            "army": {
                "isArmy": false,
                "currentArmy": []
            },
            "position": "1:5",
            "avaiableMoveLocation": ["0:1", "1:0"]

        },
        "row-two-hex-seven": {
            "income": ".50",
            "terrain": "sea",
            "army": {
                "isArmy": false,
                "currentArmy": []
            },
            "position": "1:6",
            "avaiableMoveLocation": ["0:1", "1:0"]

        },
        "row-two-hex-eight": {
            "income": ".50",
            "terrain": "sea",
            "army": {
                "isArmy": false,
                "currentArmy": []
            },
            "position": "1:7",
            "avaiableMoveLocation": ["0:1", "1:0"]

        },
        "row-two-hex-nine": {
            "income": ".50",
            "terrain": "sea",
            "army": {
                "isArmy": false,
                "currentArmy": []
            },
            "position": "1:8",
            "avaiableMoveLocation": ["0:1", "1:0"]

        },
        "row-two-hex-ten": {
            "income": ".50",
            "terrain": "sea",
            "army": {
                "isArmy": false,
                "currentArmy": []
            },
            "position": "1:9",
            "avaiableMoveLocation": ["0:1", "1:0"]

        },
        "row-two-hex-eleven": {
            "income": ".50",
            "terrain": "sea",
            "army": {
                "isArmy": false,
                "currentArmy": []
            },
            "position": "1:10",
            "avaiableMoveLocation": ["0:1", "1:0"]

        },
        "row-two-hex-twelve": {
            "income": ".50",
            "terrain": "sea",
            "army": {
                "isArmy": false,
                "currentArmy": []
            },
            "position": "1:11",
            "avaiableMoveLocation": ["0:1", "1:0"]

        },
        "row-two-hex-thirteen": {
            "income": ".50",
            "terrain": "sea",
            "army": {
                "isArmy": false,
                "currentArmy": []
            },
            "position": "1:12",
            "avaiableMoveLocation": ["0:1", "1:0"]

        },
        "row-two-hex-fourteen": {
            "income": ".50",
            "terrain": "sea",
            "army": {
                "isArmy": false,
                "currentArmy": []
            },
            "position": "1:13",
            "avaiableMoveLocation": ["0:1", "1:0"]

        },
        "row-two-hex-fifteen": {
            "income": ".50",
            "terrain": "sea",
            "army": {
                "isArmy": false,
                "currentArmy": []
            },
            "position": "1:14",
            "avaiableMoveLocation": ["0:1", "1:0"]

        },
        "row-two-hex-sixteen": {
            "income": ".50",
            "terrain": "sea",
            "army": {
                "isArmy": false,
                "currentArmy": []
            },
            "position": "1:15",
            "avaiableMoveLocation": ["0:1", "1:0"]

        },
        "row-two-hex-seventeen": {
            "income": ".50",
            "terrain": "sea",
            "army": {
                "isArmy": false,
                "currentArmy": []
            },
            "position": "1:16",
            "avaiableMoveLocation": ["0:1", "1:0"]

        }
    }
}